{"name":"Chimera","tagline":"Projeto Interdisciplinar de Desenvolvimento de Software - UEG Campus CET","body":"# Chimera\r\nProjeto Interdisciplinar de Desenvolvimento de Software - UEG Campus CET\r\n\r\nCORE Sistema: Realizar a automatização de solicitações de recursos de um sistema terceiro, visando a\r\nconexão com o mesmo via web service, facilitando e agilizando os processos envolvidos na empresa que \r\nusaria o CHIMERA.\r\n\r\n#Integrantes Equipe\r\n\r\n> Alcides Neto (Analista de Sistema)\r\n\r\n> Jean Ricardo (Desenvolvedor)\r\n\r\n> Jackeline Santos (Gerente de Projeto)\r\n\r\n> Higor Silva (Desenvolvedor)\r\n\r\n> Davis Antonio (Analista de Sistema)\r\n\r\n> Willian Brener (Estagiário)\r\n\r\n![Logo](https://filsdelhomme.files.wordpress.com/2012/12/chimera.jpg)","google":"","note":"Don't delete this file! It's used internally to help with page regeneration."}